<?xml version="1.0" encoding="UTF-8"?><record_update table="sys_atf_step">
    <sys_atf_step action="DELETE">
        <active>true</active>
        <copied_from display_value="Log">3e589b26833156102d7ce4d0deaad3fb</copied_from>
        <description>Log: Test of When needed with a date in the past should fail the business rule and fail. Record inserted by test: {{Step 2: Record Insert.Record}}</description>
        <display_name>Log</display_name>
        <inputs/>
        <inputs/>
        <mugshots_cache_json/>
        <notes/>
        <order>4</order>
        <step_config display_value="Log">58ab71985f30220012b44adb7f46661e</step_config>
        <sys_class_name>sys_atf_step</sys_class_name>
        <sys_created_by>admin</sys_created_by>
        <sys_created_on>2024-11-14 14:23:20</sys_created_on>
        <sys_id>73bb8436833556102d7ce4d0deaad339</sys_id>
        <sys_mod_count>3</sys_mod_count>
        <sys_name>Log</sys_name>
        <sys_package display_value="NeedIt" source="x_58872_needit">6ead8e780f603200cd674f8ce1050ed1</sys_package>
        <sys_policy/>
        <sys_scope display_value="NeedIt">6ead8e780f603200cd674f8ce1050ed1</sys_scope>
        <sys_update_name>sys_atf_step_73bb8436833556102d7ce4d0deaad339</sys_update_name>
        <sys_updated_by>admin</sys_updated_by>
        <sys_updated_on>2024-11-14 14:26:58</sys_updated_on>
        <table/>
        <test display_value="When needed - Past">2fbbcc72833556102d7ce4d0deaad341</test>
        <timeout/>
        <warning_message/>
    </sys_atf_step>
    <sys_variable_value action="DELETE" query="document_key=73bb8436833556102d7ce4d0deaad339"/>
    <sys_variable_value action="DELETE">
        <document>sys_atf_step</document>
        <document_key>73bb8436833556102d7ce4d0deaad339</document_key>
        <order>100</order>
        <sys_class_name>sys_variable_value</sys_class_name>
        <sys_created_by>admin</sys_created_by>
        <sys_created_on>2024-11-14 14:23:20</sys_created_on>
        <sys_id>77bb8436833556102d7ce4d0deaad33a</sys_id>
        <sys_mod_count>3</sys_mod_count>
        <sys_updated_by>admin</sys_updated_by>
        <sys_updated_on>2024-11-14 14:26:58</sys_updated_on>
        <value>Test of When needed with a date in the past should fail the business rule and fail. Record inserted by test: {{Step 2: Record Insert.Record}}</value>
        <variable display_value="Log">523c79985f30220012b44adb7f46663a</variable>
    </sys_variable_value>
    <sys_element_mapping action="DELETE" query="id=73bb8436833556102d7ce4d0deaad339"/>
    <sys_element_mapping action="DELETE">
        <field>log</field>
        <id>73bb8436833556102d7ce4d0deaad339</id>
        <sys_created_by>admin</sys_created_by>
        <sys_created_on>2024-11-14 14:23:20</sys_created_on>
        <sys_id>fbbb8436833556102d7ce4d0deaad33a</sys_id>
        <sys_mod_count>2</sys_mod_count>
        <sys_updated_by>admin</sys_updated_by>
        <sys_updated_on>2024-11-14 14:26:48</sys_updated_on>
        <table>var__m_atf_input_variable_58ab71985f30220012b44adb7f46661e</table>
        <value>Test of When needed with a date in the past should fail the business rule and fail. Record inserted by test: {{step['ebbb8436833556102d7ce4d0deaad313'].record_id}}</value>
    </sys_element_mapping>
    <sys_update_version action="INSERT_OR_UPDATE">
        <action>DELETE</action>
        <application display_value="NeedIt">6ead8e780f603200cd674f8ce1050ed1</application>
        <file_path/>
        <instance_id>6dd15a2e1b16b9d065324089bd4bcb48</instance_id>
        <instance_name>dev207010</instance_name>
        <name>sys_atf_step_73bb8436833556102d7ce4d0deaad339</name>
        <payload><![CDATA[<?xml version="1.0" encoding="UTF-8"?><record_update table="sys_atf_step"><sys_atf_step action="INSERT_OR_UPDATE"><active>true</active><copied_from display_value="Log">3e589b26833156102d7ce4d0deaad3fb</copied_from><description>Log: Test of When needed with a date in the past should fail the business rule and fail. Record inserted by test: {{Step 2: Record Insert.Record}}</description><display_name>Log</display_name><inputs/><inputs/><mugshots_cache_json/><notes/><order>4</order><step_config display_value="Log">58ab71985f30220012b44adb7f46661e</step_config><sys_class_name>sys_atf_step</sys_class_name><sys_created_by>admin</sys_created_by><sys_created_on>2024-11-14 14:23:20</sys_created_on><sys_id>73bb8436833556102d7ce4d0deaad339</sys_id><sys_mod_count>3</sys_mod_count><sys_name>Log</sys_name><sys_package display_value="NeedIt" source="x_58872_needit">6ead8e780f603200cd674f8ce1050ed1</sys_package><sys_policy/><sys_scope display_value="NeedIt">6ead8e780f603200cd674f8ce1050ed1</sys_scope><sys_update_name>sys_atf_step_73bb8436833556102d7ce4d0deaad339</sys_update_name><sys_updated_by>admin</sys_updated_by><sys_updated_on>2024-11-14 14:26:58</sys_updated_on><table/><test display_value="When needed - Past">2fbbcc72833556102d7ce4d0deaad341</test><timeout/><warning_message/></sys_atf_step><sys_variable_value action="delete_multiple" query="document_key=73bb8436833556102d7ce4d0deaad339"/><sys_variable_value action="INSERT_OR_UPDATE"><document>sys_atf_step</document><document_key>73bb8436833556102d7ce4d0deaad339</document_key><order>100</order><sys_class_name>sys_variable_value</sys_class_name><sys_created_by>admin</sys_created_by><sys_created_on>2024-11-14 14:23:20</sys_created_on><sys_id>77bb8436833556102d7ce4d0deaad33a</sys_id><sys_mod_count>3</sys_mod_count><sys_updated_by>admin</sys_updated_by><sys_updated_on>2024-11-14 14:26:58</sys_updated_on><value>Test of When needed with a date in the past should fail the business rule and fail. Record inserted by test: {{Step 2: Record Insert.Record}}</value><variable display_value="Log">523c79985f30220012b44adb7f46663a</variable></sys_variable_value><sys_element_mapping action="delete_multiple" query="id=73bb8436833556102d7ce4d0deaad339"/><sys_element_mapping action="INSERT_OR_UPDATE"><field>log</field><id>73bb8436833556102d7ce4d0deaad339</id><sys_created_by>admin</sys_created_by><sys_created_on>2024-11-14 14:23:20</sys_created_on><sys_id>fbbb8436833556102d7ce4d0deaad33a</sys_id><sys_mod_count>2</sys_mod_count><sys_updated_by>admin</sys_updated_by><sys_updated_on>2024-11-14 14:26:48</sys_updated_on><table>var__m_atf_input_variable_58ab71985f30220012b44adb7f46661e</table><value>Test of When needed with a date in the past should fail the business rule and fail. Record inserted by test: {{step['ebbb8436833556102d7ce4d0deaad313'].record_id}}</value></sys_element_mapping></record_update>]]></payload>
        <payload_hash>-562055053</payload_hash>
        <record_name>Log</record_name>
        <reverted_from/>
        <source>637f43a683fd16102d7ce4d0deaad3d9</source>
        <source_table>sys_update_set</source_table>
        <state>previous</state>
        <sys_created_by>admin</sys_created_by>
        <sys_created_on>2024-11-14 14:26:58</sys_created_on>
        <sys_id>059c0876833556102d7ce4d0deaad34c</sys_id>
        <sys_mod_count>0</sys_mod_count>
        <sys_recorded_at>1932b11fa7a0000001</sys_recorded_at>
        <sys_updated_by>admin</sys_updated_by>
        <sys_updated_on>2024-11-14 14:26:58</sys_updated_on>
        <type>Test Step</type>
        <update_guid>899c08767c355610fac683ae7f82e24b</update_guid>
        <update_guid_history>899c08767c355610fac683ae7f82e24b:-562055053,7a8c0c369c3556102ff1f6e39e86d0fa:-1134946687,b3bb8436bc355610496a0305b9390b41:-45124718,73bb84360d35561085af1f35c137da3c:-1234661646</update_guid_history>
    </sys_update_version>
    <sys_metadata_delete action="INSERT_OR_UPDATE">
        <sys_audit_delete/>
        <sys_class_name>sys_metadata_delete</sys_class_name>
        <sys_created_by>admin</sys_created_by>
        <sys_created_on>2024-11-14 14:43:43</sys_created_on>
        <sys_db_object display_value="" name="sys_atf_step">sys_atf_step</sys_db_object>
        <sys_id>0921d1aa9e1e4aa083581771a464ea19</sys_id>
        <sys_metadata>73bb8436833556102d7ce4d0deaad339</sys_metadata>
        <sys_mod_count>0</sys_mod_count>
        <sys_name>Log</sys_name>
        <sys_package display_value="NeedIt" source="x_58872_needit">6ead8e780f603200cd674f8ce1050ed1</sys_package>
        <sys_parent/>
        <sys_policy/>
        <sys_scope display_value="NeedIt">6ead8e780f603200cd674f8ce1050ed1</sys_scope>
        <sys_scope_delete display_value="">94872a8897db403e8ee69a431de2fca4</sys_scope_delete>
        <sys_update_name>sys_atf_step_73bb8436833556102d7ce4d0deaad339</sys_update_name>
        <sys_update_version display_value="sys_atf_step_73bb8436833556102d7ce4d0deaad339">059c0876833556102d7ce4d0deaad34c</sys_update_version>
        <sys_updated_by>admin</sys_updated_by>
        <sys_updated_on>2024-11-14 14:43:43</sys_updated_on>
    </sys_metadata_delete>
</record_update>
